huixiangdou/__init__.py
huixiangdou/api_server.py
huixiangdou/gradio_ui.py
huixiangdou/main.py
huixiangdou/version.py
huixiangdou/frontend/__init__.py
huixiangdou/frontend/lark.py
huixiangdou/frontend/lark_group.py
huixiangdou/frontend/wechat.py
huixiangdou/primitive/__init__.py
huixiangdou/primitive/bm250kapi.py
huixiangdou/primitive/chunk.py
huixiangdou/primitive/embedder.py
huixiangdou/primitive/entity.py
huixiangdou/primitive/faiss.py
huixiangdou/primitive/file_operation.py
huixiangdou/primitive/limitter.py
huixiangdou/primitive/llm_reranker.py
huixiangdou/primitive/query.py
huixiangdou/primitive/splitter.py
huixiangdou/primitive/token.py
huixiangdou/primitive/utils.py
huixiangdou/services/__init__.py
huixiangdou/services/config.py
huixiangdou/services/helper.py
huixiangdou/services/kg.py
huixiangdou/services/llm.py
huixiangdou/services/llm_client.py
huixiangdou/services/llm_server_hybrid.py
huixiangdou/services/parallel_pipeline.py
huixiangdou/services/prompt.py
huixiangdou/services/retriever.py
huixiangdou/services/serial_pipeline.py
huixiangdou/services/session.py
huixiangdou/services/sg_search.py
huixiangdou/services/store.py
huixiangdou/services/web_search.py
huixiangdou-20240415.dist-info/licenses/LICENSE
tests/__init__.py
tests/cp_files.py
tests/test_alles_apin.py
tests/test_bce.py
tests/test_benepar.py
tests/test_bge_reranker.py
tests/test_build_milvus_and_filter.py
tests/test_clear_kimi_files.py
tests/test_dataclass.py
tests/test_deepseek.py
tests/test_get_issue_comment_pipeline.py
tests/test_hf_import_accelerate.py
tests/test_intention_prompt.py
tests/test_internlm2.py
tests/test_kimi.py
tests/test_kimi_cr.py
tests/test_kimi_passkey.py
tests/test_llm_client.py
tests/test_m3.py
tests/test_milvus_hybrid_retrieval.py
tests/test_neo4j.py
tests/test_openai.py
tests/test_openxlab_android_api.py
tests/test_optimum_st.py
tests/test_post_android.py
tests/test_pyppeteer.py
tests/test_query_gradio.py
tests/test_qwen_react.py
tests/test_relative.py
tests/test_reranker.py
tests/test_splitter.py
huixiangdou-20240415.dist-info/METADATA
huixiangdou-20240415.dist-info/WHEEL
huixiangdou-20240415.dist-info/entry_points.txt
huixiangdou-20240415.dist-info/top_level.txt
huixiangdou-20240415.dist-info/RECORD
