Metadata-Version: 2.4
Name: huixiangdou
Version: 20240415
Summary: Overcoming Group Chat Scenarios with LLM-based Technical Assistance
Home-page: https://github.com/InternLM/huixiangdou
Author: OpenMMLab
Author-email: openmmlab@gmail.com
Classifier: Programming Language :: Python :: 3.8
Classifier: Programming Language :: Python :: 3.9
Classifier: Programming Language :: Python :: 3.10
Classifier: Programming Language :: Python :: 3.11
Classifier: Intended Audience :: Developers
Classifier: Intended Audience :: Education
Classifier: Intended Audience :: Science/Research
License-File: LICENSE
Requires-Dist: aiohttp
Requires-Dist: beautifulsoup4
Requires-Dist: duckduckgo_search
Requires-Dist: einops
Requires-Dist: loguru
Requires-Dist: lxml_html_clean
Requires-Dist: networkx>=3.0
Requires-Dist: numpy<2.0.0
Requires-Dist: openai>=1.0.0
Requires-Dist: openpyxl
Requires-Dist: pandas
Requires-Dist: pydantic>=1.10.13
Requires-Dist: pymupdf
Requires-Dist: python-docx
Requires-Dist: pytoml
Requires-Dist: readability-lxml
Requires-Dist: redis
Requires-Dist: requests
Requires-Dist: scikit-learn
Requires-Dist: db-sqlite3
Requires-Dist: texttable
Requires-Dist: tiktoken
Requires-Dist: torch>=2.0.0
Requires-Dist: transformers>=4.38
Requires-Dist: tenacity
Requires-Dist: transformers_stream_generator
Requires-Dist: unstructured
Requires-Dist: sentence_transformers
Requires-Dist: sse_starlette
Requires-Dist: fastapi
Requires-Dist: uvicorn
Requires-Dist: termcolor
Requires-Dist: opencv-python-headless
Requires-Dist: gradio>=4.41
Requires-Dist: bcembedding
Requires-Dist: jieba
Requires-Dist: faiss-gpu
Dynamic: author
Dynamic: author-email
Dynamic: classifier
Dynamic: description
Dynamic: description-content-type
Dynamic: home-page
Dynamic: license-file
Dynamic: requires-dist
Dynamic: summary
